setup.py
qama_distr/Binomialdistribution.py
qama_distr/Gaussiandistribution.py
qama_distr/Generaldistribution.py
qama_distr/__init__.py
qama_distr.egg-info/PKG-INFO
qama_distr.egg-info/SOURCES.txt
qama_distr.egg-info/dependency_links.txt
qama_distr.egg-info/not-zip-safe
qama_distr.egg-info/top_level.txt