Metadata-Version: 1.0
Name: qama-distr
Version: 0.1
Summary: Gaussian distributions
Home-page: UNKNOWN
Author: Qamarudeen Muhammad
Author-email: UNKNOWN
License: UNKNOWN
Platform: UNKNOWN
